dronewq/__init__.py
dronewq/_version.py
dronewq/core/__init__.py
dronewq/core/geometry.py
dronewq/core/georeference.py
dronewq/core/mosaic.py
dronewq/core/mosaic_methods.py
dronewq/core/plot_map.py
dronewq/core/raw_to_rss.py
dronewq/core/wq_calc.py
dronewq/ed_methods/__init__.py
dronewq/ed_methods/dls_ed.py
dronewq/ed_methods/panel_ed.py
dronewq/lw_methods/__init__.py
dronewq/lw_methods/blackpixel.py
dronewq/lw_methods/hedley.py
dronewq/lw_methods/mobley_rho.py
dronewq/masks/__init__.py
dronewq/masks/std_masking.py
dronewq/masks/threshold_masking.py
dronewq/micasense/__init__.py
dronewq/micasense/capture.py
dronewq/micasense/dls.py
dronewq/micasense/image.py
dronewq/micasense/imageset.py
dronewq/micasense/imageutils.py
dronewq/micasense/metadata.py
dronewq/micasense/panel.py
dronewq/micasense/plotutils.py
dronewq/micasense/utils.py
dronewq/utils/__init__.py
dronewq/utils/images.py
dronewq/utils/metadata.py
dronewq/utils/settings.py
dronewq/utils/utils.py
dronewq-0.1.6.dist-info/METADATA
dronewq-0.1.6.dist-info/WHEEL
dronewq-0.1.6.dist-info/licenses/LICENSE
dronewq-0.1.6.dist-info/RECORD
