Metadata-Version: 2.4
Name: dronewq
Version: 0.1.6
Summary: DroneWQ is a Python package that can be used to analyze multispectral data collected from a drone to derive ocean color radiometry and water quality properties. These scripts are specific for the MicaSense RedEdge and Altum cameras.
Project-URL: Homepage, https://github.com/aewindle110/dronewq
Project-URL: Source Code, https://github.com/aewindle110/dronewq
Project-URL: Bug Tracker, https://github.com/aewindle110/dronewq/issues
Project-URL: Documentation, https://dronewq.readthedocs.io
Project-URL: Download, https://pypi.org/project/dronewq/#files
Author: Anna Windle, Patrick Gray, Greg Silsbe
License-Expression: MIT
License-File: LICENSE
Keywords: drone,gis,remote sensing,water quality
Classifier: Development Status :: 2 - Pre-Alpha
Classifier: Intended Audience :: Science/Research
Classifier: License :: OSI Approved :: MIT License
Classifier: Operating System :: OS Independent
Classifier: Programming Language :: Python :: 3 :: Only
Classifier: Typing :: Typed
Requires-Python: <3.13,>=3.10
Requires-Dist: cameratransform==1.2
Requires-Dist: cartopy
Requires-Dist: cmocean
Requires-Dist: contextily
Requires-Dist: geopandas==1.0.1
Requires-Dist: geopy==2.4.1
Requires-Dist: imageio
Requires-Dist: mapboxgl
Requires-Dist: matplotlib==3.9.2
Requires-Dist: numpy<=1.26
Requires-Dist: opencv-python
Requires-Dist: pandas
Requires-Dist: pyexiftool<=0.4.13
Requires-Dist: pysolar
Requires-Dist: pyzbar==0.1.9
Requires-Dist: rasterio==1.3.11
Requires-Dist: rawpy==0.21.0
Requires-Dist: rioxarray
Requires-Dist: scikit-image
Requires-Dist: tqdm
Provides-Extra: dev
Requires-Dist: hatch; extra == 'dev'
Requires-Dist: pre-commit; extra == 'dev'
